primordialooze/__init__.py
primordialooze/primordialooze.py
primordialooze-0.4.0.dist-info/LICENSE
primordialooze-0.4.0.dist-info/METADATA
primordialooze-0.4.0.dist-info/WHEEL
primordialooze-0.4.0.dist-info/top_level.txt
primordialooze-0.4.0.dist-info/RECORD
