Metadata-Version: 2.1
Name: primordialooze
Version: 0.4.0
Summary: Super simple genetic algorithm library for Python.
Home-page: https://github.com/MaxStrange/primordial-ooze
Author: Max Strange
Author-email: maxfieldstrange@gmail.com
License: MIT
Keywords: machine learning genetic algorithm
Platform: UNKNOWN
Classifier: Development Status :: 3 - Alpha
Classifier: Intended Audience :: Developers
Classifier: License :: OSI Approved :: MIT License
Classifier: Operating System :: OS Independent
Classifier: Programming Language :: Python
Classifier: Programming Language :: Python :: 3
Classifier: Programming Language :: Python :: 3.5
Classifier: Programming Language :: Python :: 3.6
Classifier: Programming Language :: Python :: 3.7
Classifier: Topic :: Scientific/Engineering :: Artificial Intelligence
Classifier: Topic :: Software Development :: Libraries
Classifier: Topic :: Utilities
Requires-Python: ~=3.5
Requires-Dist: numpy
